lisa_orm/__init__.py
lisa_orm/actions.py
lisa_orm/migrate.py
lisa_orm/migrations.py
lisa_orm/search.py
lisa_orm/db/__init__.py
lisa_orm/db/models.py
lisa_orm-0.0.5.dist-info/METADATA
lisa_orm-0.0.5.dist-info/WHEEL
lisa_orm-0.0.5.dist-info/top_level.txt
lisa_orm-0.0.5.dist-info/RECORD
