Metadata-Version: 2.1
Name: lisa-orm
Version: 0.0.5
Summary: lisa is an orm semi like django orm
Home-page: https://www.facebook.com/marwanmo7amed8
Author: marawan mohamed
Author-email: marawan6569@gmail.com
License: UNKNOWN
Platform: UNKNOWN
Classifier: Development Status :: 1 - Planning
